rlrisk/__init__.py
rlrisk/agents/__init__.py
rlrisk/agents/aggressive.py
rlrisk/agents/base_agent.py
rlrisk/agents/human.py
rlrisk/environment/__init__.py
rlrisk/environment/board.bmp
rlrisk/environment/config.py
rlrisk/environment/gui.py
rlrisk/environment/risk.py
rlrisk/minigames/__init__.py
rlrisk/minigames/pick_start_positions.py
rlrisk/minigames/southern_gui.py
rlrisk/minigames/southern_warfare.py
rlrisk-1.0.2.3.dist-info/DESCRIPTION.rst
rlrisk-1.0.2.3.dist-info/METADATA
rlrisk-1.0.2.3.dist-info/RECORD
rlrisk-1.0.2.3.dist-info/WHEEL
rlrisk-1.0.2.3.dist-info/metadata.json
rlrisk-1.0.2.3.dist-info/top_level.txt
