Metadata-Version: 2.0
Name: rlrisk
Version: 1.0.2.3
Summary: A reinforcement learning environment based off the board game Risk
Home-page: https://github.com/civrev/rlrisk
Author: Christian Watts
Author-email: civrev@gmail.com
License: UNKNOWN
Platform: UNKNOWN
Requires-Python: ~=3.3
Requires-Dist: numpy (>=1.14.1)
Requires-Dist: pygame (>=1.9.3)
